{
  "username": "1sclassified",
  "entries": [
    {
      "date": "2025-12-19",
      "daily": 5171,
      "hours": 2.4180555555555556,
      "lifetime": 5171,
      "lifetimeHours": 2.4180555555555556
    },
    {
      "date": "2025-12-20",
      "daily": 12178,
      "hours": 1.9049999999999998,
      "lifetime": 17349,
      "lifetimeHours": 4.323055555555555
    },
    {
      "date": "2025-12-21",
      "daily": 2705,
      "hours": 1.8902777777777777,
      "lifetime": 20054,
      "lifetimeHours": 6.213333333333334
    },
    {
      "date": "2025-12-22",
      "daily": 178316,
      "hours": 3.363611111111111,
      "lifetime": 222464,
      "lifetimeHours": 12.908888888888889
    },
    {
      "date": "2002-12-23",
      "daily": 24094,
      "hours": 3.3319444444444444,
      "lifetime": 222464,
      "lifetimeHours": 12.908888888888889
    },
    {
      "date": "2025-12-23",
      "daily": 24094,
      "hours": 3.3319444444444444,
      "lifetime": 222464,
      "lifetimeHours": 12.908888888888889
    },
    {
      "date": "2025-12-24",
      "daily": 30408,
      "hours": 4.12611111111111,
      "lifetime": 252872,
      "lifetimeHours": 17.035
    },
    {
      "date": "2025-12-25",
      "daily": 30408,
      "hours": 4.12611111111111,
      "lifetime": 252872,
      "lifetimeHours": 17.035
    },
    {
      "date": "2025-12-31",
      "daily": 0,
      "hours": 0,
      "lifetime": 424151,
      "lifetimeHours": 26.755555555555556
    },
    {
      "date": "2026-02-01",
      "daily": 0,
      "hours": 0,
      "lifetime": 0,
      "lifetimeHours": 0
    },
    {
      "date": "2026-01-01",
      "daily": 0,
      "hours": 0,
      "lifetime": 0,
      "lifetimeHours": 0
    },
    {
      "date": "2026-01-02",
      "daily": 8095,
      "hours": 2.4605555555555556,
      "lifetime": 8095,
      "lifetimeHours": 2.4605555555555556
    },
    {
      "date": "2026-01-03",
      "daily": 19507,
      "hours": 1.6580555555555554,
      "lifetime": 27602,
      "lifetimeHours": 4.118611111111111
    }
  ]
}