{
  "username": "frozenearth1",
  "entries": [
    {
      "date": "2026-01-11",
      "daily": 0,
      "hours": 0,
      "lifetime": 0,
      "lifetimeHours": 0
    },
    {
      "date": "2026-02-12",
      "daily": 1,
      "hours": 0,
      "lifetime": 1,
      "lifetimeHours": 0
    },
    {
      "date": "2026-01-13",
      "daily": 0,
      "hours": 0,
      "lifetime": 1,
      "lifetimeHours": 0
    },
    {
      "date": "2026-01-12",
      "daily": 1,
      "hours": 0,
      "lifetime": 1,
      "lifetimeHours": 0
    },
    {
      "date": "2026-01-14",
      "daily": 0,
      "hours": 0,
      "lifetime": 1,
      "lifetimeHours": 0
    },
    {
      "date": "2026-01-15",
      "daily": 0,
      "hours": 0,
      "lifetime": 1,
      "lifetimeHours": 0
    }
  ]
}