{
  "username": "kerija_x8",
  "entries": [
    {
      "date": "2026-01-10",
      "daily": 1,
      "hours": 0.9391666666666667,
      "lifetime": 1,
      "lifetimeHours": 0.9391666666666667
    },
    {
      "date": "2026-01-11",
      "daily": 7528,
      "hours": 4.828888888888889,
      "lifetime": 7529,
      "lifetimeHours": 5.768055555555556
    },
    {
      "date": "2026-02-12",
      "daily": 2389,
      "hours": 6.7908333333333335,
      "lifetime": 9918,
      "lifetimeHours": 12.55888888888889
    },
    {
      "date": "2026-01-13",
      "daily": 0,
      "hours": 0,
      "lifetime": 9918,
      "lifetimeHours": 12.55888888888889
    },
    {
      "date": "2026-01-12",
      "daily": 2389,
      "hours": 6.7908333333333335,
      "lifetime": 9918,
      "lifetimeHours": 12.55888888888889
    },
    {
      "date": "2026-01-14",
      "daily": 0,
      "hours": 0,
      "lifetime": 9918,
      "lifetimeHours": 12.55888888888889
    }
  ]
}