{
  "username": "sum.cxx",
  "entries": [
    {
      "date": "2025-12-07",
      "daily": 255,
      "hours": 3.5280555555555555,
      "lifetime": 255,
      "lifetimeHours": 3.5280555555555555
    },
    {
      "date": "2025-12-08",
      "daily": 27,
      "hours": 2.776388888888889,
      "lifetime": 282,
      "lifetimeHours": 6.304444444444444
    },
    {
      "date": "2025-12-09",
      "daily": 730,
      "hours": 3.3461111111111115,
      "lifetime": 1012,
      "lifetimeHours": 9.650555555555556
    },
    {
      "date": "2025-12-10",
      "daily": 0,
      "hours": 0,
      "lifetime": 1012,
      "lifetimeHours": 9.650555555555556
    }
  ]
}