{
  "username": "tilly_473",
  "entries": [
    {
      "date": "2025-11-03",
      "daily": 0,
      "hours": 0,
      "lifetime": 6833,
      "lifetimeHours": 15.073888888888888
    },
    {
      "date": "2025-11-04",
      "daily": 0,
      "hours": 0,
      "lifetime": 6833,
      "lifetimeHours": 15.073888888888888
    },
    {
      "date": "2025-11-05",
      "daily": 0,
      "hours": 0,
      "lifetime": 6833,
      "lifetimeHours": 15.073888888888888
    },
    {
      "date": "2025-11-06",
      "daily": 0,
      "hours": 0,
      "lifetime": 6833,
      "lifetimeHours": 15.073888888888888
    },
    {
      "date": "2025-11-07",
      "daily": 0,
      "hours": 0,
      "lifetime": 6833,
      "lifetimeHours": 15.073888888888888
    },
    {
      "date": "2025-11-08",
      "daily": 133,
      "hours": 0.8055555555555556,
      "lifetime": 6833,
      "lifetimeHours": 15.073888888888888
    },
    {
      "date": "2025-11-09",
      "daily": 3,
      "hours": 0.9313888888888888,
      "lifetime": 6833,
      "lifetimeHours": 15.073888888888888
    },
    {
      "date": "2025-11-10",
      "daily": 36,
      "hours": 1.3941666666666666,
      "lifetime": 6833,
      "lifetimeHours": 15.073888888888888
    },
    {
      "date": "2025-11-11",
      "daily": 4864,
      "hours": 4.596666666666667,
      "lifetime": 6833,
      "lifetimeHours": 15.073888888888888
    },
    {
      "date": "2025-11-12",
      "daily": 0,
      "hours": 0.02638888888888889,
      "lifetime": 6833,
      "lifetimeHours": 15.073888888888888
    },
    {
      "date": "2025-11-13",
      "daily": 965,
      "hours": 0.9475,
      "lifetime": 6833,
      "lifetimeHours": 15.073888888888888
    },
    {
      "date": "2025-11-14",
      "daily": 0,
      "hours": 0,
      "lifetime": 6833,
      "lifetimeHours": 15.073888888888888
    },
    {
      "date": "2025-11-15",
      "daily": 51,
      "hours": 1.0675,
      "lifetime": 6833,
      "lifetimeHours": 15.073888888888888
    },
    {
      "date": "2025-11-16",
      "daily": 3,
      "hours": 0.8427777777777778,
      "lifetime": 6833,
      "lifetimeHours": 15.073888888888888
    },
    {
      "date": "2025-11-17",
      "daily": 423,
      "hours": 2.3744444444444444,
      "lifetime": 6833,
      "lifetimeHours": 15.073888888888888
    },
    {
      "date": "2025-11-18",
      "daily": 29,
      "hours": 0.7833333333333333,
      "lifetime": 6833,
      "lifetimeHours": 15.073888888888888
    },
    {
      "date": "2025-11-19",
      "daily": 325,
      "hours": 1.1177777777777778,
      "lifetime": 6833,
      "lifetimeHours": 15.073888888888888
    },
    {
      "date": "2025-11-20",
      "daily": 1,
      "hours": 0.18638888888888888,
      "lifetime": 6833,
      "lifetimeHours": 15.073888888888888
    },
    {
      "date": "2025-11-21",
      "daily": 0,
      "hours": 0,
      "lifetime": 6833,
      "lifetimeHours": 15.073888888888888
    },
    {
      "date": "2025-11-22",
      "daily": 0,
      "hours": 0,
      "lifetime": 6833,
      "lifetimeHours": 15.073888888888888
    },
    {
      "date": "2025-11-23",
      "daily": 0,
      "hours": 0,
      "lifetime": 6833,
      "lifetimeHours": 15.073888888888888
    },
    {
      "date": "2025-11-24",
      "daily": 0,
      "hours": 0,
      "lifetime": 6833,
      "lifetimeHours": 15.073888888888888
    },
    {
      "date": "2025-11-25",
      "daily": 22,
      "hours": 0.9180555555555555,
      "lifetime": 6855,
      "lifetimeHours": 15.991944444444444
    },
    {
      "date": "2025-11-26",
      "daily": 34,
      "hours": 0.46166666666666667,
      "lifetime": 6889,
      "lifetimeHours": 16.453611111111112
    },
    {
      "date": "2025-11-27",
      "daily": 0,
      "hours": 0,
      "lifetime": 6889,
      "lifetimeHours": 16.453611111111112
    },
    {
      "date": "2025-11-28",
      "daily": 0,
      "hours": 0,
      "lifetime": 6889,
      "lifetimeHours": 16.453611111111112
    },
    {
      "date": "2025-11-29",
      "daily": 0,
      "hours": 0,
      "lifetime": 6889,
      "lifetimeHours": 16.453611111111112
    }
  ]
}